jps_release_management_utils/__init__.py
jps_release_management_utils/version.py
jps_release_management_utils/scripts/__init__.py
jps_release_management_utils/scripts/full_release.py
jps_release_management_utils/scripts/help.py
jps_release_management_utils/scripts/release_project.py
jps_release_management_utils/scripts/update_changelog.py
jps_release_management_utils-0.3.0.dist-info/licenses/LICENSE
jps_release_management_utils-0.3.0.dist-info/METADATA
jps_release_management_utils-0.3.0.dist-info/WHEEL
jps_release_management_utils-0.3.0.dist-info/entry_points.txt
jps_release_management_utils-0.3.0.dist-info/top_level.txt
jps_release_management_utils-0.3.0.dist-info/RECORD
